turtleGL/__init__.py
turtleGL/example/airplane_game.py
turtleGL/example/racing_game.py
turtleGL/example/turtleGL_anime_example.py
turtleGL/example/turtleGL_cabin_example.py
turtleGL/example/turtleGL_cube_example.py
turtleGL/example/turtleGL_focal_example.py
turtleGL/example/turtleGL_from_file_example.py
turtleGL/example/turtleGL_grating_example.py
turtleGL/example/turtleGL_obj_example.py
turtleGL/example/turtleGL_plot3D_example.py
turtleGL/example/christmas tree/turtleGL_christmas_tree_example.py
turtleGL/src/camera.py
turtleGL/src/plot3d.py
turtleGL/src/scene.py
turtlegl_3d-1.2.2.dist-info/licenses/LICENSE
turtlegl_3d-1.2.2.dist-info/METADATA
turtlegl_3d-1.2.2.dist-info/WHEEL
turtlegl_3d-1.2.2.dist-info/top_level.txt
turtlegl_3d-1.2.2.dist-info/RECORD
