Metadata-Version: 2.4
Name: TurtleGL-3d
Version: 1.2.2
Summary: A 3D grafics library based on turtle
Home-page: https://github.com/MichaelHyan/turtleGL
Author: Han Yan
Author-email: Han Yan <3367461801@qq.com>
License: 
Project-URL: Homepage, https://github.com/MichaelHyan/turtleGL
Classifier: Programming Language :: Python :: 3
Classifier: License :: OSI Approved :: MIT License
Classifier: Operating System :: OS Independent
Requires-Python: >=3.8
License-File: LICENSE
Requires-Dist: numpy>=1.24.4
Requires-Dist: opencv-python>=4.12.0
Dynamic: author
Dynamic: home-page
Dynamic: license-file
Dynamic: requires-python
